{
  "1": "Rendszerhiba történt",
  "2": "Rendszerhiba történt",
  "3": "Az e-mail megadása kötelező",
  "4": "Az e-mail legfeljebb {0} karakter lehet",
  "5": "Az e-mail helytelen formátumban lett megadva",
  "6": "A kérés objektuma kötelező",
  "7": "A dátum formátuma helytelen ennél: {0}",
  "8": "A személyazonosító szám megadása kötelező",
  "9": "A személyazonosító szám legfeljebb {0} karakter lehet",
  "10": "A személyazonosító szám legalább {0} karakter hosszú kell legyen",
  "11": "Érvénytelen kérés",
  "12": "Érvénytelen kártyaszám",
  "13": "Érvénytelen lejárati hónap",
  "14": "Érvénytelen lejárati év",
  "15": "Érvénytelen CVC",
  "16": "A kártyabirtokos neve kötelező",
  "17": "A kártyád lejárati dátuma érvénytelen",
  "18": "A(z) {0} személyazonosító szám helytelen formátumban lett megadva",
  "19": "A kártyabirtokos neve legfeljebb {0} karakter lehet",
  "20": "A ConversationId legfeljebb {0} karakter lehet",
  "21": "A kártya aliasa legfeljebb {0} karakter lehet",
  "22": "Az IP legfeljebb {0} karakter lehet",
  "23": "A visszahívási URL (Callback URL) megadása kötelező",
  "24": "{0} megadása kötelező",
  "25": "A GSM szám megadása kötelező",
  "26": "A GSM szám legfeljebb {0} karakter lehet",
  "27": "Érvénytelen telefonszám",
  "28": "Érvénytelen metaadat formátum",
  "29": "A követelési token megadása kötelező",
  "30": "A tagsági azonosító megadása kötelező",
  "31": "A ConversationId rosszindulatú kódot tartalmazhat",
  "1000": "Érvénytelen aláírás",
  "1001": "Az API adatok nem találhatók",
  "1002": "Kereskedő nem található",
  "1003": "Hitelesítési hiba",
  "1004": "Véletlenszerű karakterlánc megadása kötelező",
  "1005": "A kérés objektuma kötelező",
  "1006": "API kulcs megadása kötelező",
  "1007": "Az aláírás megadása kötelező",
  "1008": "Az Authorization fejléc előtagja nem található",
  "1009": "Az Authorization fejléc értéke kötelező",
  "1010": "Gateway kereskedő nem található",
  "1011": "A jóváhagyott kereskedő és a kereskedői szám nem egyeznek",
  "1012": "Aktív platform nem található",
  "1013": "A megadott alkalmazásnévhez nem tartozik felhasználó",
  "1014": "Biztonsági információ nem található",
  "1015": "Az alkalmazás neve kötelező",
  "2000": "Ez a szolgáltatás csak marketplace ügyfelek számára érhető el",
  "2001": "Alkereskedő nem található",
  "2002": "Az alkereskedő már létezik",
  "2003": "A subMerchantKey megadása kötelező",
  "2004": "A subMerchantType megadása kötelező",
  "2005": "Az IBAN megadása kötelező",
  "2007": "A subMerchantExternalId megadása kötelező",
  "2008": "A subMerchantExternalId legfeljebb {0} karakter lehet",
  "2009": "A cím megadása kötelező",
  "2010": "A cím legfeljebb {0} karakter lehet",
  "2011": "A cím legalább {0} karakter hosszú kell legyen",
  "2012": "A kapcsolattartó neve kötelező",
  "2013": "A kapcsolattartó neve legfeljebb {0} karakter lehet",
  "2014": "A kapcsolattartó neve legalább {0} karakter hosszú kell legyen",
  "2015": "A kapcsolattartó vezetékneve kötelező",
  "2016": "A kapcsolattartó vezetékneve legfeljebb {0} karakter lehet",
  "2017": "A kapcsolattartó vezetékneve legalább {0} karakter hosszú kell legyen",
  "2018": "Adóhivatal megadása kötelező",
  "2019": "Az adóhivatal neve legfeljebb {0} karakter lehet",
  "2020": "Az adóhivatal neve legalább {0} karakter kell legyen",
  "2021": "A cég hivatalos neve kötelező",
  "2022": "A cég neve legfeljebb {0} karakter lehet",
  "2023": "A cég neve legalább {0} karakter hosszú kell legyen",
  "2024": "Adószám megadása kötelező",
  "2025": "Az adószám legfeljebb {0} karakter lehet",
  "2026": "Az adószám legalább {0} karakter kell legyen",
  "2027": "Az adóhivatal neve {0} csak betűket tartalmazhat",
  "2028": "A név legfeljebb {0} karakter lehet",
  "2029": "A GSM szám legfeljebb {0} karakter lehet",
  "2030": "A megadott IBAN formátuma érvénytelen",
  "2031": "A kapcsolattartó neve {0} betűből kell álljon",
  "2032": "A kapcsolattartó vezetékneve {0} betűből kell álljon",
  "2033": "A cég hivatalos neve {0} alfanumerikus karakterből kell álljon",
  "2034": "A GSM szám nem tartalmazhat betűket",
  "2035": "Az adószám csak számokat tartalmazhat",
  "2036": "A SWIFT kód megadása kötelező",
  "2037": "Az alkereskedő számlájának pénznemének meg kell egyeznie a helyi számláéval",
  "2038": "A török lírás IBAN-oknak TR-rel kell kezdődniük",
  "2039": "A SWIFT kód legfeljebb {0} karakter lehet",
  "2040": "Érvénytelen utalási megjegyzés",
  "1401": "A kártyaszám megadása kötelező",
  "3000": "Az externalId legfeljebb {0} karakter lehet",
  "3001": "A cardUserKey megadása kötelező",
  "3002": "A cardToken megadása kötelező",
  "3003": "A kártyaadatok megadása kötelező",
  "3004": "Hiba történt a kártya mentése során",
  "3005": "A cardUserKey nem található",
  "3006": "A cardToken nem található",
  "3007": "A kártyatárolás funkció nincs definiálva",
  "3008": "Titkosítási hiba",
  "3009": "Visszafejtési hiba",
  "3010": "A kártya nem található",
  "3011": "A kártya felhasználói kulcsa nem egyezik",
  "3012": "Az email nem tartalmazhat kártyaszámot",
  "3013": "Az externalId nem tartalmazhat kártyaszámot",
  "3014": "A merchantId megadása kötelező",
  "3015": "A changeManagementId megadása kötelező",
  "3016": "Az anonymizationType megadása kötelező",
  "3017": "Hiba történt a kártya anonimizálása során",
  "3018": "A kártyatárolási tiltólista funkció nincs definiálva",
  "3019": "Nem található aktív tiltólista",
  "3020": "Már létezik aktív tiltólista",
  "3021": "Hiba történt a kártya felhasználójának frissítése során",
  "3022": "A toMerchantId megadása kötelező",
  "4000": "A subMerchantKey megadása kötelező",
  "4001": "Az indoklás megadása kötelező",
  "4002": "A partnerkereskedő nem található",
  "4003": "Nincs egyenlegrekord a küldőhöz",
  "4004": "A küldő egyenlege nem elegendő",
  "4005": "A kereskedő nem jogosult az elszámolási szolgáltatás használatára",
  "4006": "Az elszámoláshoz a partnerkereskedő egyenlegfeltöltési beállítását ki kell kapcsolni",
  "10005": "Hiba történt a fizetési folyamat során, kérjük, lépjen kapcsolatba a bankjával.",
  "10012": "Hiba történt a fizetési folyamat során, kérjük, lépjen kapcsolatba a bankjával.",
  "10034": "A tranzakciót a bank nem engedélyezte.",
  "10041": "Túllépte a PIN próbálkozások számát, a tranzakciót a bank elutasította.",
  "10043": "A tranzakciót a bank nem engedélyezte.",
  "10051": "Elégtelen kártyalimit, nem elegendő egyenleg.",
  "10054": "Érvénytelen lejárati dátum. A kártyája lejárt.",
  "10057": "Kártyája nem engedélyezett ehhez a tranzakcióhoz, kérjük, forduljon a bankjához.",
  "10058": "Hiba történt a fizetés során, kérjük, lépjen kapcsolatba a cég képviselőjével.",
  "10084": "A megadott CVV érték hibás vagy érvénytelen.",
  "10093": "Kártyája le van tiltva online vásárlásra, kérjük, lépjen kapcsolatba a bankjával.",
  "10201": "A kártya elutasította a tranzakciót, kérjük, forduljon a bankjához.",
  "10202": "Hiba történt a fizetési folyamat során, kérjük, lépjen kapcsolatba a cég képviselőjével.",
  "10204": "Hiba történt a fizetési folyamat során, kérjük, lépjen kapcsolatba a cég képviselőjével.",
  "10205": "Az e-mail cím formátuma érvénytelen, kérjük, ellenőrizze a címet.",
  "10207": "Kérjük, szerezze be a bank jóváhagyását.",
  "10208": "Hiba történt a fizetés során, kérjük, lépjen kapcsolatba a cég képviselőjével.",
  "10209": "A kártya blokkolva van, kérjük, forduljon a bankjához.",
  "10210": "Hibás CVC információ, próbálja meg újra.",
  "10211": "Hiba történt a fizetés során, kérjük, forduljon a bankjához.",
  "10212": "Túllépte a hibás CVC próbálkozások számát, kérjük, forduljon a bankjához.",
  "10213": "A BIN nem található, kérjük, lépjen kapcsolatba a cég képviselőjével.",
  "10214": "Hiba történt a banknál, próbálja újra később.",
  "10215": "Érvénytelen kártya, hibás kártyaszám, kérjük, ellenőrizze a számot.",
  "10216": "Hiba történt a banknál, próbálja újra később.",
  "10217": "A tranzakciót 3D Secure módban kell végrehajtani.",
  "10218": "A részletfizetés nem engedélyezett betéti kártyákkal, próbálja meg újra.",
  "10219": "Hiba történt a banknál, próbálja újra később.",
  "10220": "Kérjük, próbálja meg újra. Ha a hiba továbbra is fennáll, forduljon a bankjához.",
  "10221": "Külföldi kártyákkal nem engedélyezett tranzakció, kérjük, lépjen kapcsolatba a cég képviselőjével.",
  "10222": "A POS nem támogatja a részletfizetést, kérjük, lépjen kapcsolatba a cég képviselőjével.",
  "10223": "A POS számára napzárás szükséges.",
  "10224": "A kártya tranzakciós limitje túllépve, kérjük, forduljon a bankjához.",
  "10225": "Kártyája nem engedélyezett ehhez a tranzakcióhoz, kérjük, forduljon a bankjához.",
  "10226": "Túllépte a PIN próbálkozások számát, kérjük, forduljon a bankjához.",
  "10227": "Hibás PIN, kérjük, próbálja meg újra.",
  "10228": "Hiba történt a banknál, próbálja újra később.",
  "10229": "Hibás lejárati dátum, kérjük, próbálja újra.",
  "10230": "A fizetési kérés blokkolva lett a bank által, kérjük, forduljon a bankjához.",
  "10231": "Az értékesítési összeg nem lehet kevesebb, mint a felhasznált pontok.",
  "10232": "Érvénytelen összeg, kérjük, forduljon a bankjához.",
  "10233": "Érvénytelen kártyatípus, kérjük, forduljon a bankjához.",
  "10234": "Nincs elegendő pont.",
  "10235": "American Express kártyahiba, kérjük, forduljon a bankjához.",
  "10237": "Betéti kártyás tranzakciókhoz nem engedélyezett visszatérítés.",
  "10238": "Érvénytelen tranzakció.",
  "10239": "A fizetést a felhasználó megszakította.",
  "10240": "A kérés időtúllépéssel megszakadt.",
  "10241": "Kommunikációs vagy rendszerhiba.",
  "10242": "Kommunikációs vagy rendszerhiba.",
  "10243": "A fizetést nem fogadták el.",
  "10244": "A fizetést nem fogadták el.",
  "10245": "A visszatérítés összege és a korábbi visszatérítések nem haladhatják meg a részlet összegét.",
  "10246": "Jelenleg nem lehet visszatérítést végrehajtani alternatív fizetési móddal végzett tranzakcióra, próbálja később újra.",
  "10247": "A banki átutalásos fizetés nem történt meg.",
  "10248": "A kívánt összeg meghaladja a tranzakciós limitet, kérjük, forduljon a bankjához.",
  "10249": "Hiba történt az egyenlegfizetés során, kérjük, lépjen kapcsolatba a cég képviselőjével.",
  "10250": "Pontok nem használhatók részletfizetéses tranzakcióknál.",
  "10251": "Pontokat és kártyalimiteket nem lehet egyidejűleg használni ennél a kártyánál."
}
