{
  "1": "సిస్టమ్ లో లోపం ఏర్పడింది",
  "2": "సిస్టమ్ లో లోపం ఏర్పడింది",
  "3": "ఈమెయిల్ తప్పనిసరిగా ఇవ్వాలి",
  "4": "ఈమెయిల్ గరిష్ఠంగా {0} అక్షరాల వరకు ఉండాలి",
  "5": "ఈమెయిల్ తప్పు ఫార్మాట్‌లో పంపబడింది",
  "6": "అభ్యర్థన వస్తువు తప్పనిసరిగా ఇవ్వాలి",
  "7": "{0} కోసం తేదీ ఫార్మాట్ తప్పుగా ఉంది",
  "8": "గుర్తింపు సంఖ్య తప్పనిసరిగా ఇవ్వాలి",
  "9": "గుర్తింపు సంఖ్య గరిష్ఠంగా {0} అక్షరాలు ఉండాలి",
  "10": "గుర్తింపు సంఖ్య కనీసం {0} అక్షరాలు ఉండాలి",
  "11": "చెల్లని అభ్యర్థన",
  "12": "చెల్లని కార్డ్ నంబర్",
  "13": "చెల్లని గడువు నెల",
  "14": "చెల్లని గడువు సంవత్సరం",
  "15": "చెల్లని CVC",
  "16": "కార్డ్ హోల్డర్ పేరు తప్పనిసరిగా ఇవ్వాలి",
  "17": "మీ కార్డ్ గడువు తేదీ చెల్లదు",
  "18": "గుర్తింపు సంఖ్య {0} తప్పు ఫార్మాట్‌లో పంపబడింది",
  "19": "కార్డ్ హోల్డర్ పేరు గరిష్ఠంగా {0} అక్షరాలు ఉండాలి",
  "20": "ConversationId గరిష్ఠంగా {0} అక్షరాలు ఉండాలి",
  "21": "కార్డ్ అలియాస్ గరిష్ఠంగా {0} అక్షరాలు ఉండాలి",
  "22": "IP గరిష్ఠంగా {0} అక్షరాలు ఉండాలి",
  "23": "Callback URL తప్పనిసరిగా ఇవ్వాలి",
  "24": "{0} తప్పనిసరిగా ఇవ్వాలి",
  "25": "GSM నంబర్ తప్పనిసరిగా ఇవ్వాలి",
  "26": "GSM నంబర్ గరిష్ఠంగా {0} అక్షరాలు ఉండాలి",
  "27": "చెల్లని ఫోన్ నంబర్",
  "28": "చెల్లని మెటాడేటా ఫార్మాట్",
  "29": "Claim టోకెన్ తప్పనిసరిగా ఇవ్వాలి",
  "30": "మెంబర్ ID తప్పనిసరిగా ఇవ్వాలి",
  "31": "ConversationId హానికరమైన కోడ్‌ను కలిగి ఉండవచ్చు",
  "1000": "చెల్లని సంతకం",
  "1001": "API వివరాలు లభించలేదు",
  "1002": "మర్చంట్ కనుగొనబడలేదు",
  "1003": "అధికార లోపం",
  "1004": "యాదృచ్ఛిక స్ట్రింగ్ తప్పనిసరిగా ఇవ్వాలి",
  "1005": "అభ్యర్థన వస్తువు తప్పనిసరిగా ఇవ్వాలి",
  "1006": "API కీ తప్పనిసరిగా ఇవ్వాలి",
  "1007": "సంతకం తప్పనిసరిగా ఇవ్వాలి",
  "1008": "అథరైజేషన్ హెడ్డర్ ప్రిఫిక్స్ కనిపించలేదు",
  "1009": "అథరైజేషన్ హెడ్డర్ స్ట్రింగ్ తప్పనిసరిగా ఇవ్వాలి",
  "1010": "గేట్వే మర్చంట్ కనుగొనబడలేదు",
  "1011": "అధికారిక మర్చంట్ మరియు మర్చంట్ నంబర్ సరిపోలడం లేదు",
  "1012": "క్రియాశీల ప్లాట్‌ఫారమ్ కనుగొనబడలేదు",
  "1013": "అప్లికేషన్ పేరు ఉన్న వినియోగదారు కనబడలేదు",
  "1014": "భద్రతా సమాచారం కనుగొనబడలేదు",
  "1015": "అప్లికేషన్ పేరు తప్పనిసరిగా ఇవ్వాలి",
  "2000": "ఈ సేవ మార్కెట్‌ప్లేస్ కస్టమర్లకు మాత్రమే అందుబాటులో ఉంది",
  "2001": "ఉప మర్చంట్ కనుగొనబడలేదు",
  "2002": "ఉప మర్చంట్ ఇప్పటికే ఉంది",
  "2003": "subMerchantKey తప్పనిసరిగా ఇవ్వాలి",
  "2004": "subMerchantType తప్పనిసరిగా ఇవ్వాలి",
  "2005": "IBAN తప్పనిసరిగా ఇవ్వాలి",
  "2007": "subMerchantExternalId తప్పనిసరిగా ఇవ్వాలి",
  "2008": "subMerchantExternalId గరిష్ఠంగా {0} అక్షరాలు ఉండాలి",
  "2009": "చిరునామా తప్పనిసరిగా ఇవ్వాలి",
  "2010": "చిరునామా గరిష్ఠంగా {0} అక్షరాలు ఉండాలి",
  "2011": "చిరునామా కనీసం {0} అక్షరాలు ఉండాలి",
  "2012": "సంప్రదింపు పేరు తప్పనిసరిగా ఇవ్వాలి",
  "2013": "సంప్రదింపు పేరు గరిష్ఠంగా {0} అక్షరాలు ఉండాలి",
  "2014": "సంప్రదింపు పేరు కనీసం {0} అక్షరాలు ఉండాలి",
  "2015": "సంప్రదింపు ఇంటిపేరు తప్పనిసరిగా ఇవ్వాలి",
  "2016": "ఇంటిపేరు గరిష్ఠంగా {0} అక్షరాలు ఉండాలి",
  "2017": "ఇంటిపేరు కనీసం {0} అక్షరాలు ఉండాలి",
  "2018": "పన్ను కార్యాలయం తప్పనిసరిగా ఇవ్వాలి",
  "2019": "పన్ను కార్యాలయం గరిష్ఠంగా {0} అక్షరాలు ఉండాలి",
  "2020": "పన్ను కార్యాలయం కనీసం {0} అక్షరాలు ఉండాలి",
  "2021": "కానూను ప్రకారం కంపెనీ పేరు తప్పనిసరిగా ఇవ్వాలి",
  "2022": "కంపెనీ పేరు గరిష్ఠంగా {0} అక్షరాలు ఉండాలి",
  "2023": "కంపెనీ పేరు కనీసం {0} అక్షరాలు ఉండాలి",
  "2024": "పన్ను నంబర్ తప్పనిసరిగా ఇవ్వాలి",
  "2025": "పన్ను నంబర్ గరిష్ఠంగా {0} అక్షరాలు ఉండాలి",
  "2026": "పన్ను నంబర్ కనీసం {0} అక్షరాలు ఉండాలి",
  "2027": "పన్ను కార్యాలయం {0} అక్షరాలతో మాత్రమే ఉండాలి",
  "2028": "పేరు గరిష్ఠంగా {0} అక్షరాలు ఉండాలి",
  "2029": "GSM నంబర్ గరిష్ఠంగా {0} అక్షరాలు ఉండాలి",
  "2030": "పంపబడిన IBAN చెల్లని ఫార్మాట్‌లో ఉంది",
  "2031": "సంప్రదింపు పేరు {0} అక్షరాలు ఉండాలి",
  "2032": "ఇంటిపేరు {0} అక్షరాలు ఉండాలి",
  "2033": "కంపెనీ పేరు {0} ఆల్ఫాన్యూమరిక్ అక్షరాలు ఉండాలి",
  "2034": "GSM నంబర్లో అక్షరాలు ఉండకూడదు",
  "2035": "పన్ను నంబర్ సంఖ్యలతో మాత్రమే ఉండాలి",
  "2036": "SWIFT కోడ్ తప్పనిసరిగా ఇవ్వాలి",
  "2037": "ఉప మర్చంట్ ఖాతా కరెన్సీ స్థానిక ఖాతా కరెన్సీతో సరిపోవాలి",
  "2038": "టర్కిష్ లీరా ఖాతాల IBAN 'TR'తో ప్రారంభం కావాలి",
  "2039": "SWIFT కోడ్ గరిష్ఠంగా {0} అక్షరాలు ఉండాలి",
  "2040": "చెల్లని బదిలీ వివరణ",
  "1401": "కార్డ్ నంబర్ తప్పనిసరిగా ఇవ్వాలి",
  "3000": "externalId గరిష్ఠంగా {0} అక్షరాలు ఉండాలి",
  "3001": "cardUserKey తప్పనిసరి",
  "3002": "cardToken తప్పనిసరి",
  "3003": "కార్డు సమాచారం అవసరం",
  "3004": "కార్డును నిల్వ చేసే సమయంలో లోపం వచ్చింది",
  "3005": "cardUserKey కనుగొనబడలేదు",
  "3006": "cardToken కనుగొనబడలేదు",
  "3007": "కార్డు నిల్వ చేసే ఫీచర్ నిర్వచించబడలేదు",
  "3008": "ఎన్‌క్రిప్షన్ లోపం",
  "3009": "డీ-క్రిప్షన్ లోపం",
  "3010": "కార్డు కనుగొనబడలేదు",
  "3011": "కార్డు వినియోగదారు కీ సరిపోలలేదు",
  "3012": "ఇమెయిల్‌లో కార్డు నంబర్ ఉండకూడదు",
  "3013": "externalId లో కార్డు నంబర్ ఉండకూడదు",
  "3014": "merchantId సమాచారం తప్పనిసరి",
  "3015": "changeManagementId సమాచారం తప్పనిసరి",
  "3016": "anonymizationType సమాచారం తప్పనిసరి",
  "3017": "కార్డు అనామకరణ సమయంలో లోపం వచ్చింది",
  "3018": "కార్డు నిల్వ బ్లాకుల జాబితా ఫీచర్ నిర్వచించబడలేదు",
  "3019": "చురుకైన బ్లాకుల జాబితా ఏదీ కనుగొనబడలేదు",
  "3020": "ఒక చురుకైన బ్లాకుల జాబితా ఇప్పటికే ఉంది",
  "3021": "కార్డు వినియోగదారుని నవీకరించేటప్పుడు లోపం",
  "3022": "toMerchantId సమాచారం తప్పనిసరి",
  "4000": "subMerchantKey తప్పనిసరి",
  "4001": "కారణం తప్పనిసరి",
  "4002": "ఉప-వాణిజ్యదారుడు కనుగొనబడలేదు",
  "4003": "పంపిన వారి కోసం బ్యాలెన్స్ రికార్డు లేదు",
  "4004": "పంపినవారి బ్యాలెన్స్ సరిపోలడం లేదు",
  "4005": "వాణిజ్యదారుడు సెటిల్మెంట్ సేవను ఉపయోగించేందుకు అర్హుడు కాదు",
  "4006": "సెటిల్మెంట్ చేయాలంటే, ఉప-వాణిజ్యదారుడి సెట్టింగ్ 'ఫండ్స్‌ను బ్యాలెన్స్‌కి పంపడం' నిలిపివేయాలి",
  "10005": "చెల్లింపు ప్రక్రియలో లోపం ఏర్పడింది, దయచేసి మీ బ్యాంకును సంప్రదించండి.",
  "10012": "చెల్లింపు ప్రక్రియలో లోపం ఏర్పడింది, దయచేసి మీ బ్యాంకును సంప్రదించండి.",
  "10034": "బ్యాంకు లావాదేవీని అనుమతించలేదు.",
  "10041": "PIN ప్రయత్నాల పరిమితి మించిపోయింది, బ్యాంకు లావాదేవీని అనుమతించలేదు.",
  "10043": "లావాదేవీని బ్యాంకు అనుమతించలేదు.",
  "10051": "కార్డ్‌లో పరిమితి లేదా బ్యాలెన్స్ సరిపోదు.",
  "10054": "తేదీ చెల్లదు. మీ కార్డ్ గడువు ముగిసింది.",
  "10057": "ఈ లావాదేవీకి మీ కార్డ్ పరిమితి పెట్టబడింది, దయచేసి మీ బ్యాంకును సంప్రదించండి.",
  "10058": "చెల్లింపు సమయంలో లోపం ఏర్పడింది, దయచేసి సంస్థ ప్రతినిధిని సంప్రదించండి.",
  "10084": "నివేశించిన CVV విలువ తప్పుగా ఉంది లేదా చెల్లదు.",
  "10093": "మీ కార్డ్ ఆన్‌లైన్ కొనుగోళ్లకు మూసివేయబడింది, దయచేసి మీ బ్యాంకును సంప్రదించండి.",
  "10201": "కార్డ్ లావాదేవీని అనుమతించలేదు, దయచేసి మీ బ్యాంకును సంప్రదించండి.",
  "10202": "చెల్లింపు ప్రక్రియలో లోపం ఏర్పడింది, దయచేసి సంస్థ ప్రతినిధిని సంప్రదించండి.",
  "10204": "చెల్లింపు ప్రక్రియలో లోపం ఏర్పడింది, దయచేసి సంస్థ ప్రతినిధిని సంప్రదించండి.",
  "10205": "ఈమెయిల్ ఫార్మాట్ తప్పు, దయచేసి మీ చిరునామాను తనిఖీ చేయండి.",
  "10207": "దయచేసి మీ బ్యాంక్ నుండి ఆమోదం పొందండి.",
  "10208": "చెల్లింపు సమయంలో లోపం ఏర్పడింది, దయచేసి సంస్థ ప్రతినిధిని సంప్రదించండి.",
  "10209": "కార్డ్ బ్లాక్ చేయబడింది, దయచేసి మీ బ్యాంకును సంప్రదించండి.",
  "10210": "CVC సమాచారం తప్పు, దయచేసి మళ్లీ ప్రయత్నించండి.",
  "10211": "చెల్లింపు సమయంలో లోపం ఏర్పడింది, దయచేసి మీ బ్యాంకును సంప్రదించండి.",
  "10212": "CVC తప్పు ప్రయత్నాల పరిమితిని మించి వెళ్లారు, దయచేసి మీ బ్యాంకును సంప్రదించండి.",
  "10213": "BIN కనుగొనబడలేదు, దయచేసి సంస్థ ప్రతినిధిని సంప్రదించండి.",
  "10214": "బ్యాంక్ లోపం ఏర్పడింది, దయచేసి తర్వాత మళ్లీ ప్రయత్నించండి.",
  "10215": "చెల్లని కార్డ్, తప్పు కార్డ్ నంబర్, దయచేసి తనిఖీ చేయండి.",
  "10216": "బ్యాంక్ లోపం ఏర్పడింది, దయచేసి తర్వాత మళ్లీ ప్రయత్నించండి.",
  "10217": "ఈ లావాదేవీ 3D Secure ద్వారా చేయాలి.",
  "10218": "డెబిట్ కార్డ్‌లతో ఇన్‌స్టాల్‌మెంట్లు అనుమతించబడవు, దయచేసి మళ్లీ ప్రయత్నించండి.",
  "10219": "బ్యాంక్ లోపం ఏర్పడింది, దయచేసి తర్వాత మళ్లీ ప్రయత్నించండి.",
  "10220": "దయచేసి మళ్లీ ప్రయత్నించండి. లోపం కొనసాగితే, మీ బ్యాంకును సంప్రదించండి.",
  "10221": "విదేశీ కార్డ్‌లతో లావాదేవీలు అనుమతించబడవు, దయచేసి సంస్థ ప్రతినిధిని సంప్రదించండి.",
  "10222": "POS లో ఇన్‌స్టాల్‌మెంట్ లావాదేవీలు అనుమతించబడలేదు, సంస్థ ప్రతినిధిని సంప్రదించండి.",
  "10223": "POS కోసం రోజుకుగల ముగింపు అవసరం.",
  "10224": "మీ కార్డ్ లావాదేవీ పరిమితిని మించిపోయింది, దయచేసి మీ బ్యాంకును సంప్రదించండి.",
  "10225": "ఈ లావాదేవీకి మీ కార్డ్ పరిమితి పెట్టబడింది, దయచేసి మీ బ్యాంకును సంప్రదించండి.",
  "10226": "PIN ప్రయత్నాల పరిమితిని మించి వెళ్లారు, దయచేసి మీ బ్యాంకును సంప్రదించండి.",
  "10227": "PIN తప్పు, మళ్లీ ప్రయత్నించండి.",
  "10228": "బ్యాంక్ లోపం ఏర్పడింది, దయచేసి తర్వాత మళ్లీ ప్రయత్నించండి.",
  "10229": "కార్డ్ ముగింపు తేదీ తప్పు, మళ్లీ ప్రయత్నించండి.",
  "10230": "బ్యాంక్ ద్వారా చెల్లింపు అభ్యర్థన నిరాకరించబడింది, దయచేసి మీ బ్యాంకును సంప్రదించండి.",
  "10231": "విక్రయ మొత్తం వాడిన పాయింట్ల కంటే తక్కువగా ఉండకూడదు.",
  "10232": "చెల్లని మొత్తం, దయచేసి మీ బ్యాంకును సంప్రదించండి.",
  "10233": "చెల్లని కార్డ్ రకం, దయచేసి మీ బ్యాంకును సంప్రదించండి.",
  "10234": "పాయింట్లు సరిపోవు.",
  "10235": "American Express కార్డ్ లోపం, దయచేసి మీ బ్యాంకును సంప్రదించండి.",
  "10237": "డెబిట్ కార్డ్ లావాదేవీలకు రీఫండ్‌లు అనుమతించబడవు.",
  "10238": "చెల్లని లావాదేవీ.",
  "10239": "వినియోగదారు చెల్లింపును రద్దు చేశారు.",
  "10240": "పంపిన అభ్యర్థన గడువు ముగిసింది.",
  "10241": "కమ్యూనికేషన్ లేదా సిస్టమ్ లోపం.",
  "10242": "కమ్యూనికేషన్ లేదా సిస్టమ్ లోపం.",
  "10243": "చెల్లింపు ఆమోదించబడలేదు.",
  "10244": "చెల్లింపు ఆమోదించబడలేదు.",
  "10245": "రిఫండ్ మొత్తం మరియు ఇప్పటికే రీఫండ్ చేసిన మొత్తం మొత్తం ఇన్‌స్టాల్‌మెంట్ మొత్తాన్ని మించకూడదు.",
  "10246": "ఈ ప్రత్యామ్నాయ చెల్లింపు పద్ధతితో లావాదేవీకి ప్రస్తుతం రీఫండ్ చేయడం సాధ్యపడదు, దయచేసి తర్వాత మళ్లీ ప్రయత్నించండి.",
  "10247": "బ్యాంక్ ట్రాన్స్‌ఫర్ చెల్లింపు చేయబడలేదు.",
  "10248": "మీరు చేయదలచిన మొత్తం లావాదేవీ పరిమితిని మించిపోతోంది, దయచేసి మీ బ్యాంకును సంప్రదించండి.",
  "10249": "మిగిలిన మొత్తం చెల్లించే సమయంలో లోపం ఏర్పడింది, సంస్థ ప్రతినిధిని సంప్రదించండి.",
  "10250": "ఇన్‌స్టాల్‌మెంట్ లావాదేవీలకు పాయింట్లు ఉపయోగించలేరు.",
  "10251": "ఈ కార్డ్‌తో లావాదేవీకి పాయింట్లు మరియు కార్డ్ పరిమితిని ఒకేసారి ఉపయోగించలేరు."
}
